salary_stone/__init__.py
salary_stone/metrics.py
salary_stone/salary_extractor.py
salary_stone/skill_extractor.py
salary_stone/skill_recommender.py
salary_stone/data/en_core_web_sm-3.4.0-py3-none-any.whl
salary_stone/data/jz_skill_patterns.jsonl
salary_stone/data/model.pkl
salary_stone-0.4.0.dist-info/AUTHORS.rst
salary_stone-0.4.0.dist-info/LICENSE
salary_stone-0.4.0.dist-info/METADATA
salary_stone-0.4.0.dist-info/WHEEL
salary_stone-0.4.0.dist-info/top_level.txt
salary_stone-0.4.0.dist-info/RECORD
