Metadata-Version: 2.1
Name: salary-stone
Version: 0.4.0
Summary: The purpose of this project is to host the methods related to the salary stone project. These include a skill extractor from text, a model that allows for prediction of and a variety of other method.
Home-page: https://github.com/nickmayn/salary_stone
Author: Nick Maynard
Author-email: nickmayn@vt.edu
License: Apache Software License 2.0
Keywords: salary_stone
Classifier: Development Status :: 2 - Pre-Alpha
Classifier: Intended Audience :: Developers
Classifier: License :: OSI Approved :: Apache Software License
Classifier: Natural Language :: English
Classifier: Programming Language :: Python :: 3
Classifier: Programming Language :: Python :: 3.6
Classifier: Programming Language :: Python :: 3.7
Classifier: Programming Language :: Python :: 3.8
Requires-Python: >=3.6
License-File: LICENSE
License-File: AUTHORS.rst
